pdf_decomposer/__init__.py
pdf_decomposer/adobe_service.py
pdf_decomposer/base_decomposer.py
pdf_decomposer/open_decomposer.py
pdf_decomposer/paddle_decomposer.py
pdf_decomposer/rebuild_table.py
pdf_decomposer-0.2.1.dist-info/LICENSE
pdf_decomposer-0.2.1.dist-info/METADATA
pdf_decomposer-0.2.1.dist-info/WHEEL
pdf_decomposer-0.2.1.dist-info/RECORD
