Metadata-Version: 2.1
Name: pdf-decomposer
Version: 0.2.1
Summary: Extract structured information from images, tables, and text in PDF document.
Home-page: https://github.com/marswen/pdf-decomposer
License: AGPL-3.0
Keywords: pdf,layout,table extraction
Author: marswen
Author-email: dongwen930910@foxmail.com
Classifier: License :: OSI Approved :: GNU Affero General Public License v3
Classifier: Programming Language :: Python :: 2
Classifier: Programming Language :: Python :: 2.7
Classifier: Programming Language :: Python :: 3
Classifier: Programming Language :: Python :: 3.4
Classifier: Programming Language :: Python :: 3.5
Classifier: Programming Language :: Python :: 3.6
Classifier: Programming Language :: Python :: 3.7
Classifier: Programming Language :: Python :: 3.8
Classifier: Programming Language :: Python :: 3.9
Classifier: Programming Language :: Python :: 3.10
Classifier: Programming Language :: Python :: 3.11
Classifier: Programming Language :: Python :: 3.12
Requires-Dist: layoutparser (==0.3.4)
Requires-Dist: loguru (==0.7.2)
Requires-Dist: paddleocr (==2.7.0.2)
Requires-Dist: pdfservices-sdk (==2.3.0)
Requires-Dist: pytesseract (==0.3.10)
Requires-Dist: tqdm (==4.65.0)
